README.md
setup.py
cryptohash/__init__.py
cryptohash/md5.py
cryptohash/sha1.py
cryptohash/sha224.py
cryptohash/sha256.py
cryptohash/sha384.py
cryptohash/sha512.py
cryptohash.egg-info/PKG-INFO
cryptohash.egg-info/SOURCES.txt
cryptohash.egg-info/dependency_links.txt
cryptohash.egg-info/top_level.txt