Metadata-Version: 2.1
Name: cryptohash
Version: 1.0.5
Summary: Tiny hashing module that uses the native crypto API in Python
Home-page: https://yoginth.com
Author: Yoginth
Author-email: me@yoginth.com
License: UNKNOWN
Project-URL: Patreon, https://www.patreon.com/yoginth
Project-URL: Source, https://gitlab.com/yoginth/cryptohash
Platform: UNKNOWN
Classifier: Programming Language :: Python
Classifier: Natural Language :: English
Classifier: Environment :: Plugins
Classifier: Operating System :: OS Independent
Classifier: Intended Audience :: Developers
Classifier: License :: OSI Approved :: MIT License
